seq2seq/__init__.py
seq2seq/dataset.py
seq2seq/model.py
seq2seq/tokenizer.py
seq2seq_pytorch-0.1.2.dist-info/LICENSE.txt
seq2seq_pytorch-0.1.2.dist-info/METADATA
seq2seq_pytorch-0.1.2.dist-info/WHEEL
seq2seq_pytorch-0.1.2.dist-info/top_level.txt
seq2seq_pytorch-0.1.2.dist-info/RECORD
