Metadata-Version: 2.1
Name: seq2seq-pytorch
Version: 0.1.2
Summary: Industrial-grade implementation of seq2seq algorithm based on Pytorch, integrated beam search algorithm.
Home-page: https://github.com/Chiang97912/seq2seq
Author: Chiang97912
Author-email: chiang97912@gmail.com
License: UNKNOWN
Keywords: seq2seq
Platform: UNKNOWN
Classifier: Development Status :: 3 - Alpha
Classifier: Intended Audience :: Developers
Classifier: Topic :: Scientific/Engineering :: Artificial Intelligence
Classifier: License :: OSI Approved :: MIT License
Classifier: Programming Language :: Python :: 3.6
License-File: LICENSE.txt
Requires-Dist: torch (>=1.9.0)
Requires-Dist: torchtext (>=0.3.1)
Requires-Dist: nltk (>=3.5)
Requires-Dist: numpy (>=1.19.5)
Requires-Dist: jieba (>=0.42.1)
